{
    "start": [],
    "rating": [
        "general",
        "sensitive",
        "questionable",
        "explicit"
    ],
    "character": [
        "#{character.one}",
        "#{character.boys}",
        "#{character.girls}",
        "#{character.others}",
        "#{character.age}",
        "#{character.focus}",
        "$^toned(.*)",
        "no humans"
    ],
    "animal": [
        "creature",
        "animal",
        "#{type.animal}"
    ],
    "framing": [
        "close-up",
        "portrait",
        "upper body",
        "lower body",
        "cowboy shot",
        "full body",
        "$(.*) focus$"
    ],
    "body": {
        "skin": [
            "$(.*) skin$",
            "$^dark-skinned (.*)"
        ],
        "sweat": [
            "sweat",
            "sweatdrop"
        ],
        "hand": {
            "gloves": [
                "gloves",
                "#{type.colors} gloves",
                "$(.*) gloves$",
                "goggles",
                "$^goggles (.*)"
            ],
            "face": [
                "$(.*) face$",
                "$(.*)blush(.*)"
            ],
            "hat": [
                "hat",
                "#{type.colors} hat",
                "$(.*) hat$",
                "cap",
                "#{type.colors} cap",
                "$(.*) cap$",
                "helmet",
                "headwear",
                "#{type.colors} headwear",
                "$(.*) headwear$"
            ],
            "hair": [
                "#{body/hair.colors}",
                "#{body/hair.length}",
                "#{body/hair.hairstyles}"
            ],
            "eyebrows": [
                "$(.*) eyebrows$",
                "hikimayu",
                "eyebrow piercing",
                "eyebrow cut",
                "frown"
            ],
            "eyes": [
                "heterochromia",
                "#{type.colors} eyes",
                "blank eyes",
                "no sclera",
                "#{type.colors} sclera",
                "$(.*)eye(.*)",
                "$(.*)eyes$",
                "sanpaku"
            ],
            "nose": [
                "nose",
                "$(.*) nose$"
            ],
            "mouth": [
                "$(.*)teeth(.*)",
                "$(.*)fang(.*)",
                "tusks",
                "$(.*)tongue(.*)",
                "$(.*)lips(.*)",
                "open mouth",
                "closed mouth",
                "$(.*)mouth$",
                "$(.*)smile$",
                "grin"
            ],
            "mask": [
                "$(.*) mask$"
            ],
            "ears": [
                "kemonomimi mode",
                "floppy ears",
                "hair ears",
                "animal ears",
                "$(.*)ear fluff$",
                "#{type.animal} ears",
                "$(.*) ears"
            ]
        },
        "nude": [
            "$^topless(.*)",
            "$(.*)nude(.*)",
            "$(.*)collarbone$",
            "pectorals",
            "$(.*)nipples$",
            "abs",
            "navel"
        ],
        "censoring": [
            "censor",
            "$(.*)censor(.*)"
        ],
        "upper_body": {
            "scarf": [
                "scarf",
                "$(.*)scarf$",
                "#{type.colors} scarf"
            ],
            "shirt": [
                "$(.*)shirt$",
                "#{type.colors} shirt",
                "$(.*)coat$",
                "#{type.colors} coat",
                "$(.*)jacket$",
                "#{type.colors} jacket",
                "$(.*)hoodie$",
                "#{type.colors} hoodie",
                "$(.*)tank top",
                "#{type.colors} tank top",
                "hood",
                "$^hood (.*)$",
                "$(.*)sleeves$",
                "$^sleeves(.*)"
            ],
            "watch": [
                "ring",
                "$(.*)(\\-|\\s)ring$",
                "watch",
                "wristwatch"
            ],
            "bag": [
                "$^(.*)bag",
                "backpack"
            ]
        },
        "tail": [
            "tail",
            "$(.*)tail fluff$",
            "$(.*) tail$"
        ],
        "wings": [
            "$(.*)wings$"
        ],
        "down_body": {
            "pants": [
                "pants",
                "$(.*) pants$",
                "#{type.colors} pants",
                "shorts",
                "$(.*) shorts$",
                "#{type.colors} shorts",
                "swim trunks",
                "male swimwear",
                "$(.*) male swimwear$",
                "#{type.colors} male swimwear$",
                "jumpsuit",
                "bulge"
            ],
            "legs": [
                "$^legs(.*)",
                "$^leg(.*)",
                "$(.*)legs$",
                "$(.*)leg$"
            ],
            "footwear": [
                "shoes",
                "$(.*)shoes$",
                "boots",
                "sneakers",
                "#{type.colors} footwear",
                "barefoot"
            ]
        },
        "clothes": [
            "$(.*)clothes$",
            "$(.*)uniform$"
        ]
    },
    "actions": [
        "#{actions.all_pose}"
    ],
    "kaomoji": [
        "#{expression.kaomoji}"
    ],
    "background": [
        "sparkle",
        "simple background",
        "#{type.colors} background",
        "outdoors",
        "indoors",
        "sky",
        "#{type.colors} sky"
    ],
    "misc": [],
    "end": [],
    "blacklist": [
        "#{character_blacklist}",
        "#{blacklist}"
    ]
}